frw/__init__.py
frw/compare_faces.py
frw/detect_faces.py
python_face_recognition_wrapper-0.2.0.dist-info/LICENSE
python_face_recognition_wrapper-0.2.0.dist-info/METADATA
python_face_recognition_wrapper-0.2.0.dist-info/WHEEL
python_face_recognition_wrapper-0.2.0.dist-info/top_level.txt
python_face_recognition_wrapper-0.2.0.dist-info/RECORD
